README
mdtime.py
setup.py
mdtime.egg-info/PKG-INFO
mdtime.egg-info/SOURCES.txt
mdtime.egg-info/dependency_links.txt
mdtime.egg-info/top_level.txt