Metadata-Version: 1.0
Name: mdtime
Version: 1.0
Summary: mdtime checks the time of a tpr file or cpt file, or compare the two to see if cpt < tpr
Home-page: http://www.zhuyixue.com
Author: Zhuyi Xue
Author-email: zhuyi.xue@mail.utoronto.ca
License: GPLv3
Keywords: molecular dynamics gromacs time
Platform: unix-like
